lexiconalgorithm/__init__.py
lexiconalgorithm/booster.py
lexiconalgorithm/emoticon.py
lexiconalgorithm/emotion_new.csv
lexiconalgorithm/neg.txt
lexiconalgorithm/neg1.txt
lexiconalgorithm/sentileye.py
lexiconalgorithm/sentileye_list.csv
lexiconalgorithm/slang.csv
SentiLEYE-0.1.dist-info/LICENSE.txt
SentiLEYE-0.1.dist-info/METADATA
SentiLEYE-0.1.dist-info/WHEEL
SentiLEYE-0.1.dist-info/top_level.txt
SentiLEYE-0.1.dist-info/RECORD
