Metadata-Version: 2.1
Name: SentiLEYE
Version: 0.1
Summary: A sentiment lexicon algorithm to classify pidgin English and English text into positive, negative or neutral
Home-page: UNKNOWN
Author: Bayode Ogunleye
Author-email: batoog101@yahoo.com
License: UNKNOWN
Platform: UNKNOWN
Classifier: License :: OSI Approved :: MIT License
Classifier: Programming Language :: Python :: 3
Classifier: Operating System :: OS Independent
License-File: LICENSE.txt
